nvl/__init__.py
nvl/cli.py
nvl-0.2.1.dist-info/LICENSE
nvl-0.2.1.dist-info/METADATA
nvl-0.2.1.dist-info/WHEEL
nvl-0.2.1.dist-info/entry_points.txt
nvl-0.2.1.dist-info/top_level.txt
nvl-0.2.1.dist-info/RECORD
