Metadata-Version: 2.1
Name: nvl
Version: 0.2.1
Summary: A CLI tool to initialize directories.
Home-page: https://github.com/yourusername/nvl
Author: Your Name
Author-email: your.email@example.com
Classifier: Programming Language :: Python :: 3
Classifier: License :: OSI Approved :: MIT License
Classifier: Operating System :: OS Independent
Requires-Python: >=3.6
License-File: LICENSE
